<?xml version="1.0" encoding="UTF-8" standalone="no"?><Entities build="b349" majorVersion="8" minorVersion="3" modelPersistenceProviderPackage="H2PersistenceProviderPackage" revision="0" schemaVersion="1030" universal=""><DataShapes><DataShape baseDataShape="" description="" documentationContent="" homeMashup="" lastModifiedDate="2018-08-21T12:46:05.087+03:00" name="GitBackup.CommitInfo.DataShape" projectName="GitBackup" tags=""><Owner name="Administrator" type="User"/><avatar/><DesignTimePermissions><Create/><Read/><Update/><Delete/><Metadata/></DesignTimePermissions><RunTimePermissions/><VisibilityPermissions><Visibility/></VisibilityPermissions><ConfigurationTables/><FieldDefinitions><FieldDefinition aspect.isPrimaryKey="false" baseType="STRING" description="" name="Author" ordinal="3"/><FieldDefinition aspect.dataShape="GitBackup.CommitChangedFiles.DataShape" aspect.isPrimaryKey="false" baseType="INFOTABLE" description="" name="ChangedFiles" ordinal="7"/><FieldDefinition aspect.isPrimaryKey="false" baseType="STRING" description="" name="CommitDescription" ordinal="6"/><FieldDefinition aspect.isPrimaryKey="false" baseType="STRING" description="" name="Commiter" ordinal="5"/><FieldDefinition aspect.isPrimaryKey="false" baseType="STRING" description="" name="CommitID" ordinal="1"/><FieldDefinition aspect.isPrimaryKey="false" baseType="DATETIME" description="" name="Date" ordinal="4"/><FieldDefinition aspect.isPrimaryKey="false" baseType="STRING" description="" name="Parents" ordinal="2"/></FieldDefinitions><ConfigurationChanges><ConfigurationChange changeAction="CREATE" changeReason="" timestamp="2018-08-21T12:46:05.087+03:00" user="Administrator"/></ConfigurationChanges></DataShape></DataShapes></Entities>